{
  "page_state": "YouTube video page showing a video player with an error message 'Something went wrong. Refresh or try again later.' The video title is 'Unmatched Clarity and Depth in 8K HDR 60fps Dolby Vision'. The right sidebar shows a list of recommended videos.",
  "blockers": [],
  "previous_action_result": "SUCCESS - Clicked on 'video with lion thumbnail' and navigated to the video page, but the video player shows an error",
  "key_elements": [
    "Video player showing error message",
    "Video title: 'Unmatched Clarity and Depth in 8K HDR 60fps Dolby Vision'",
    "Subscribe button below video title",
    "Like, Share, Download buttons below video title",
    "List of recommended videos in right sidebar"
  ],
  "goal_progress": "BLOCKED"
}